{"acadYear": "2020/2021", "preclusion": "All non-architecture students", "description": "This module will provide the opportunity for students to demonstrate their understanding and ability in integrating technology with architecture. Topics - The module will demand more comprehensive response in developing an appropriate technological response to the particular demands of architecture, climate and context. Students have to demonstrate ability in the design development process and a degree of innovation in integrating technological ideas and components into the architectural project.", "title": "Design 7", "department": "Architecture", "faculty": "Design and Environment", "workload": [2, 3, 0, 3, 12], "prerequisite": "AR3101  Design 5 Grade 'C'; AR3102  Design 6 Grade 'C'", "moduleCredit": "8", "moduleCode": "AR4101", "attributes": {"fyp": true}, "semesterData": []}