{"acadYear": "2020/2021", "description": "This module introduces students to the systematic analysis of the grammar of modern standard English. We will examine common topics in the phonology, morphology and syntax of the English language. The effect of language contact on English will also be discussed. The module is descriptive in nature. Through examining the grammar of English, students will be exposed to important analytical concepts in corpus and theoretical linguistics.", "title": "The Grammar of Modern English", "department": "English Language and Literature", "faculty": "Arts and Social Science", "workload": [0, 3, 0, 2, 5], "prerequisite": "Must be registered as a Graduate Student in the University or with the approval of the Department", "moduleCredit": "5", "moduleCode": "EL5202R", "attributes": {"mpes2": true}, "aliases": ["EL5202"], "semesterData": [{"semester": 2, "timetable": [{"classNo": "1", "startTime": "1800", "endTime": "2100", "weeks": [1, 2, 3, 4, 5, 6, 7, 8, 9, 10, 11, 12, 13], "venue": "AS1-0201", "day": "Wednesday", "lessonType": "Seminar-Style Module Class", "size": 1, "covidZone": "A"}], "covidZones": ["A"]}]}