{"acadYear": "2020/2021", "preclusion": "FIN3120E", "description": "This module aims to do the following: - To provide students with an overview of the commodity markets as an asset class - To introduce key concepts for commodity trading and investing businesses - To provide a framework for assessing risks and opportunities for investors in physical commodity assets.", "title": "TIF: Physical Commodity Markets and Assets", "department": "Finance", "faculty": "NUS Business School", "workload": [0, 3, 0, 4, 3], "prerequisite": "FIN2704/FIN2704X and FIN3703.", "moduleCredit": "4", "moduleCode": "FIN3761D", "semesterData": [], "prereqTree": {"and": [{"or": ["FIN2704", "FIN2704X"]}, "FIN3703"]}}