{"acadYear": "2020/2021", "description": "This module introduces Southeast Asia\u2019s past from earliest times to the present (1st century to 21st century). It highlights how processes of interaction, circulation, and connection shaped the key characteristics and worldviews that are associated with the region today. Module content will focus on how local communities adopted and adapted influences from around the world to form a distinctive regional culture. How polities emerged via the region\u2019s historical interaction with Indian, Chinese, Islamic, Iberian, European, Japanese, and New World civilizations will be given special attention. Today\u2019s nation-states and regional organizations are a product of this long history of community formation.", "title": "Introduction to Southeast Asian History", "department": "History", "faculty": "Arts and Social Science", "workload": [2, 1, 0, 0, 7], "moduleCredit": "4", "moduleCode": "HY2250", "attributes": {"mpes2": true, "su": true}, "semesterData": []}