{"acadYear": "2020/2021", "preclusion": "IE5105 Modeling for Supply Chain Systems", "description": "Distribution and Transportation are two of the important\ndrivers for supply chain. This module focuses on the the\nbasic concepts, modelling technologies and solution\nmethods for these two drivers. It will also introduce how\nthe decision making for these two drivers will impact the\nefficiency and the effectiveness of the supply chain\nsystem.", "title": "Supply Chain: Distribution and Transportation", "department": "Industrial Systems Engineering and Management", "faculty": "Engineering", "workload": [3, 0, 0, 3, 4], "moduleCredit": "2", "moduleCode": "IE5105B", "attributes": {"grsu": true, "ssgf": true}, "semesterData": []}