{"acadYear": "2020/2021", "preclusion": "LL4285/LL5285/LL6285/LC5285 International Dispute Settlement", "description": "This seminar will explore key legal questions related to\ninternational dispute settlement with a view to providing a\nbroad overview of the field with respect to State-to-State,\nInvestor-State, and commercial disputes. This course will\ninclude a discussion of the various types of international\ndisputes and settlement mechanisms available for their\nresolution. It will explore the law pertaining to dispute\nsettlement before the ICJ, WTO, ITLOS, as well as\ninternational arbitration, both Investor-State arbitration and\ncommercial arbitration. The course will compare these\ndifferent legal processes on issues such as jurisdiction,\nprovisional remedies/measures, equal treatment,\nevidence, and enforcement.", "title": "International Dispute Settlement", "department": "FoL Dean's Office", "faculty": "Law", "workload": [0, 3, 0, 0, 7], "prerequisite": "NUS Compulsory Core Curriculum or its equivalent", "moduleCredit": "5", "moduleCode": "LC5285V", "attributes": {"ssgf": true}, "aliases": ["LL4285V", "LL5285V", "LL6285V"], "semesterData": [{"semester": 1, "timetable": [{"classNo": "2", "startTime": "0900", "endTime": "1200", "weeks": [1, 2, 3, 4, 5, 6, 7, 8, 9, 10, 11, 12, 13], "venue": "E-Learn_D", "day": "Friday", "lessonType": "Seminar-Style Module Class", "size": 50, "covidZone": "Unknown"}], "covidZones": ["Unknown"]}]}