{"acadYear": "2020/2021", "description": "This module will serve as an introduction to Vocal Pedagogy and will consist of a survey of the current literature on the subject as well as supervised teaching of a beginning level voice student. Course requirements include extensive reading, written assignments, in-class presentations, and mid-term and final examinations.", "title": "Vocal Pedagogy", "department": "YSTCM Dean's Office", "faculty": "YST Conservatory of Music", "workload": [4, 0, 2, 0, 4], "moduleCredit": "4", "moduleCode": "MUA4215", "attributes": {"lab": true, "ssgf": true}, "semesterData": [{"semester": 1, "timetable": [{"classNo": "1", "startTime": "1600", "endTime": "1730", "weeks": [1, 2, 3, 4, 5, 6, 7, 8, 9, 10, 11, 12, 13], "venue": "YSTCM-SR4", "day": "Tuesday", "lessonType": "Sectional Teaching", "size": 10, "covidZone": "A"}, {"classNo": "1", "startTime": "1600", "endTime": "1730", "weeks": [1, 2, 3, 4, 5, 6, 7, 8, 9, 10, 11, 12, 13], "venue": "YSTCM-SR4", "day": "Friday", "lessonType": "Sectional Teaching", "size": 10, "covidZone": "A"}], "covidZones": ["A"]}]}