{"acadYear": "2020/2021", "description": "This module explores foundational principles of\ncommunity nursing practice including epidemiology,\nsocial determinants of health, and primary health care\nfrom a philosophical basis and a model of service\nprovision using the World Health Organisation\u2019s global\nframework for health. This module includes one day per\nweek community attachment.", "title": "Community Integrated Health Care", "department": "Alice Lee Center for Nursing Studies", "faculty": "Yong Loo Lin Sch of Medicine", "workload": [1, 2, 0, 4, 3], "moduleCredit": "4", "moduleCode": "NUR3117", "attributes": {"mpes1": true, "mpes2": true}, "semesterData": [{"semester": 1, "timetable": [{"classNo": "1", "startTime": "1500", "endTime": "1600", "weeks": [7], "venue": "E-Learn_B", "day": "Wednesday", "lessonType": "Lecture", "size": 227, "covidZone": "Unknown"}, {"classNo": "12", "startTime": "1000", "endTime": "1200", "weeks": [1, 2, 3, 4, 5, 6, 7, 8, 9, 10, 11, 12, 13], "venue": "E-Learn_B", "day": "Friday", "lessonType": "Tutorial", "size": 20, "covidZone": "Unknown"}, {"classNo": "14", "startTime": "1200", "endTime": "1400", "weeks": [2, 3, 4, 5, 6, 7, 8, 9, 10, 11, 12, 13], "venue": "E-Learn_B", "day": "Friday", "lessonType": "Tutorial", "size": 20, "covidZone": "Unknown"}, {"classNo": "2", "startTime": "1000", "endTime": "1200", "weeks": [2, 3, 4, 5, 6, 7, 8, 9, 10, 11, 12, 13], "venue": "E-Learn_B", "day": "Thursday", "lessonType": "Tutorial", "size": 20, "covidZone": "Unknown"}, {"classNo": "3", "startTime": "0800", "endTime": "1000", "weeks": [1, 2, 3, 4, 5, 6, 7, 8, 9, 10, 11, 12, 13], "venue": "E-Learn_B", "day": "Thursday", "lessonType": "Tutorial", "size": 20, "covidZone": "Unknown"}, {"classNo": "4", "startTime": "0800", "endTime": "1000", "weeks": [1, 2, 3, 4, 5, 6, 7, 8, 9, 10, 11, 12, 13], "venue": "E-Learn_B", "day": "Thursday", "lessonType": "Tutorial", "size": 20, "covidZone": "Unknown"}, {"classNo": "6", "startTime": "1600", "endTime": "1800", "weeks": [2, 3, 4, 5, 6, 7, 8, 9, 10, 11, 12, 13], "venue": "E-Learn_B", "day": "Thursday", "lessonType": "Tutorial", "size": 20, "covidZone": "Unknown"}, {"classNo": "10", "startTime": "1400", "endTime": "1600", "weeks": [1, 2, 3, 4, 5, 6, 7, 8, 9, 10, 11, 12, 13], "venue": "E-Learn_B", "day": "Thursday", "lessonType": "Tutorial", "size": 20, "covidZone": "Unknown"}, {"classNo": "8", "startTime": "0800", "endTime": "1000", "weeks": [1, 2, 3, 4, 5, 6, 7, 8, 9, 10, 11, 12, 13], "venue": "E-Learn_B", "day": "Friday", "lessonType": "Tutorial", "size": 20, "covidZone": "Unknown"}, {"classNo": "1", "startTime": "0800", "endTime": "1000", "weeks": [1], "venue": "E-Learn_B", "day": "Thursday", "lessonType": "Tutorial", "size": 20, "covidZone": "Unknown"}, {"classNo": "7", "startTime": "0800", "endTime": "1000", "weeks": [1, 2, 3, 4, 5, 6, 7, 8, 9, 10, 11, 12, 13], "venue": "E-Learn_B", "day": "Friday", "lessonType": "Tutorial", "size": 20, "covidZone": "Unknown"}, {"classNo": "13", "startTime": "1200", "endTime": "1400", "weeks": [2, 3, 4, 5, 6, 7, 8, 9, 10, 11, 12, 13], "venue": "E-Learn_B", "day": "Friday", "lessonType": "Tutorial", "size": 20, "covidZone": "Unknown"}, {"classNo": "11", "startTime": "1000", "endTime": "1200", "weeks": [1, 2, 3, 4, 5, 6, 7, 8, 9, 10, 11, 12, 13], "venue": "E-Learn_B", "day": "Friday", "lessonType": "Tutorial", "size": 20, "covidZone": "Unknown"}, {"classNo": "14", "startTime": "1000", "endTime": "1200", "weeks": [1], "venue": "E-Learn_B", "day": "Friday", "lessonType": "Tutorial", "size": 20, "covidZone": "Unknown"}, {"classNo": "5", "startTime": "1600", "endTime": "1800", "weeks": [2, 3, 4, 5, 6, 7, 8, 9, 10, 11, 12, 13], "venue": "E-Learn_B", "day": "Thursday", "lessonType": "Tutorial", "size": 20, "covidZone": "Unknown"}, {"classNo": "1", "startTime": "1000", "endTime": "1200", "weeks": [2, 3, 4, 5, 6, 7, 8, 9, 10, 11, 12, 13], "venue": "E-Learn_B", "day": "Thursday", "lessonType": "Tutorial", "size": 20, "covidZone": "Unknown"}, {"classNo": "9", "startTime": "1400", "endTime": "1600", "weeks": [1, 2, 3, 4, 5, 6, 7, 8, 9, 10, 11, 12, 13], "venue": "E-Learn_B", "day": "Thursday", "lessonType": "Tutorial", "size": 20, "covidZone": "Unknown"}, {"classNo": "2", "startTime": "0800", "endTime": "1000", "weeks": [1], "venue": "E-Learn_B", "day": "Thursday", "lessonType": "Tutorial", "size": 20, "covidZone": "Unknown"}, {"classNo": "5", "startTime": "1400", "endTime": "1600", "weeks": [1], "venue": "E-Learn_B", "day": "Thursday", "lessonType": "Tutorial", "size": 20, "covidZone": "Unknown"}, {"classNo": "13", "startTime": "1000", "endTime": "1200", "weeks": [1], "venue": "E-Learn_B", "day": "Friday", "lessonType": "Tutorial", "size": 20, "covidZone": "Unknown"}, {"classNo": "1", "startTime": "1200", "endTime": "1300", "weeks": [3], "venue": "E-Learn_B", "day": "Wednesday", "lessonType": "Lecture", "size": 227, "covidZone": "Unknown"}, {"classNo": "6", "startTime": "1400", "endTime": "1600", "weeks": [1], "venue": "E-Learn_B", "day": "Thursday", "lessonType": "Tutorial", "size": 20, "covidZone": "Unknown"}], "covidZones": ["Unknown"]}]}