{"acadYear": "2020/2021", "description": "The module presents basic computational methods useful for physics and science students. The lectures cover: (1) Basic numerical methods - differentiation, integration, interpolation, root-finding and random number generators, (2) Differential equations - finite difference method, shooting method and relaxation method; applications to chaotic dynamics of a driven pendulum, one-dimensional Schr\u00f6dinger equation, and fast Fourier transform, (3) Matrices - Gaussian elimination scheme for a system of linear equations, eigenvalues of Hermitian matrices;  Hartree-Fock approximation, (4) Monte Carlo simulations - sampling and integration; random walk and simulation of diffusion equation, stochastic differential equation, Brownian dynamics; variational Monte Carlo simulation; Metropolis algorithm and Ising model, and (5) Finite element methods - basic concepts; applications to the Poisson equation in electrostatics.", "title": "Computational Methods in Physics", "department": "Physics", "faculty": "Science", "workload": [3, 1, 0, 1, 5], "prerequisite": "Students who have passed PC2134 or equivalent", "moduleCredit": "4", "moduleCode": "PC3236", "attributes": {"mpes2": true}, "semesterData": [{"semester": 2, "timetable": [{"classNo": "1", "startTime": "1200", "endTime": "1400", "weeks": [1, 2, 3, 4, 5, 6, 7, 8, 9, 10, 11, 12, 13], "venue": "E-Learn_B", "day": "Tuesday", "lessonType": "Lecture", "size": 60, "covidZone": "Unknown"}, {"classNo": "1", "startTime": "1200", "endTime": "1400", "weeks": [1, 2, 3, 4, 5, 6, 7, 8, 9, 10, 11, 12, 13], "venue": "E-Learn_B", "day": "Thursday", "lessonType": "Lecture", "size": 60, "covidZone": "Unknown"}], "covidZones": ["Unknown"]}], "prereqTree": "PC2134", "fulfillRequirements": ["PC5215", "PC3238"]}