{"acadYear": "2020/2021", "description": "Various modules requiring applied expertise in the selected fields of psychology will be offered from time to time by visiting or local staff.", "title": "Selected Applications in Psychology", "department": "Psychology", "faculty": "Arts and Social Science", "workload": [3, 0, 0, 2, 5], "prerequisite": "Consent of instructor", "moduleCredit": "4", "moduleCode": "PL6215", "semesterData": [{"semester": 1, "timetable": [], "covidZones": []}, {"semester": 2, "timetable": [], "covidZones": []}]}