{"acadYear": "2020/2021", "description": "This module will 1) explore the features, applications, benefits and risks of AI and Data on social policy (education, healthcare, insurance, social safety nets), employment and wages, fiscal policy (taxation and expenditure), transport and smart cities and implications for politics and social cohesion (fakenews, deep fake, election manipulation); 2) understand their implications for Singapore; and 3) understand the policy and regulatory implications in terms of growth, equity, security, privacy, efficiency and risk management. The module will be comparative in perspective and will draw from the experience of the US, China, Europe, Japan and Singapore.", "title": "Artificial Intelligence, Data and Public Policy", "department": "LKYSPP Dean's Office", "faculty": "LKY School of Public Policy", "workload": [9.75, 0, 0, 9.75, 13], "moduleCredit": "1", "moduleCode": "PP5023", "attributes": {"ssgf": true}, "semesterData": [{"semester": 1, "timetable": [{"classNo": "1", "startTime": "1800", "endTime": "2100", "weeks": [5], "venue": "E-Learn_E", "day": "Wednesday", "lessonType": "Lecture", "size": 90, "covidZone": "Unknown"}, {"classNo": "1", "startTime": "1800", "endTime": "2100", "weeks": [5], "venue": "E-Learn_D", "day": "Monday", "lessonType": "Lecture", "size": 90, "covidZone": "Unknown"}, {"classNo": "1", "startTime": "1800", "endTime": "2100", "weeks": [5], "venue": "E-Learn_D", "day": "Friday", "lessonType": "Lecture", "size": 90, "covidZone": "Unknown"}], "covidZones": ["Unknown"]}]}