{"acadYear": "2020/2021", "description": "This course serves as an advanced introduction to modern macroeconomic\nanalysis to understand the causes and consequences of macroeconomic\nfluctuations. We will explore at a deeper level some of the topics covered in\nIntermediate Macroeconomics, as well as some other research topics. Topics\ncovered may include economic growth, business cycles, financial markets,\nmonetary and fiscal policy etc.", "title": "Advanced Macroeconomics", "department": "Yale-NUS College", "faculty": "Yale-NUS College", "workload": [0, 4, 0, 0, 8.5], "prerequisite": "YSS2214 Intermediate Macroeconomics or with the permission of the instructor.", "moduleCredit": "5", "moduleCode": "YSS3248", "semesterData": [{"semester": 1, "timetable": [{"classNo": "1", "startTime": "1430", "endTime": "1600", "weeks": [1, 2, 3, 4, 5, 6, 7, 8, 9, 10, 11, 12, 13], "venue": "Y-PerfHall", "day": "Saturday", "lessonType": "Seminar-Style Module Class", "size": 18, "covidZone": "A"}, {"classNo": "1", "startTime": "1430", "endTime": "1600", "weeks": [1, 2, 3, 4, 5, 6, 7, 8, 9, 10, 11, 12, 13], "venue": "Y-PerfHall", "day": "Thursday", "lessonType": "Seminar-Style Module Class", "size": 18, "covidZone": "A"}, {"classNo": "1", "startTime": "0900", "endTime": "1000", "weeks": [1, 2, 3, 4, 5, 6, 7, 8, 9, 10, 11, 12, 13], "venue": "E-Learn_A", "day": "Monday", "lessonType": "Seminar-Style Module Class", "size": 18, "covidZone": "Unknown"}], "covidZones": ["A", "Unknown"], "examDate": "2020-12-01T01:00:00.000Z", "examDuration": 180}], "prereqTree": "YSS2214"}